qaner/__init__.py
qaner/arg_parse.py
qaner/data_utils.py
qaner/dataset.py
qaner/inference.py
qaner/inference_utils.py
qaner/metrics.py
qaner/train.py
qaner/train_utils.py
qaner/utils.py
qaner-0.1.1.dist-info/LICENSE
qaner-0.1.1.dist-info/METADATA
qaner-0.1.1.dist-info/WHEEL
qaner-0.1.1.dist-info/entry_points.txt
qaner-0.1.1.dist-info/top_level.txt
qaner-0.1.1.dist-info/RECORD
