Metadata-Version: 2.1
Name: qaner
Version: 0.1.1
Summary: Unofficial implementation of QaNER: Prompting Question Answering Models for Few-shot Named Entity Recognition.
Home-page: https://github.com/dayyass/qaner
Author: Dani El-Ayyass
Author-email: dayyass@yandex.ru
License: UNKNOWN
Platform: UNKNOWN
Requires-Dist: numpy (==1.21.6)
Requires-Dist: tensorboard (==2.9.0)
Requires-Dist: torch (==1.8.1)
Requires-Dist: tqdm (==4.64.0)
Requires-Dist: transformers (==4.19.2)
